cnocr/__init__.py
cnocr/__version__.py
cnocr/app.py
cnocr/clf_cli.py
cnocr/cli.py
cnocr/cn_ocr.py
cnocr/consts.py
cnocr/dataset.py
cnocr/dataset_utils.py
cnocr/gradio_app.py
cnocr/gradio_app2.py
cnocr/label_cn.txt
cnocr/label_number.txt
cnocr/line_split.py
cnocr/lr_scheduler.py
cnocr/recognizer.py
cnocr/serve.py
cnocr/trainer.py
cnocr/utils.py
cnocr/classification/__init__.py
cnocr/classification/dataset.py
cnocr/classification/image_classifier.py
cnocr/data_utils/__init__.py
cnocr/data_utils/aug.py
cnocr/data_utils/block_shuffle.py
cnocr/data_utils/transforms.py
cnocr/data_utils/utils.py
cnocr/models/__init__.py
cnocr/models/ctc.py
cnocr/models/densenet.py
cnocr/models/mobilenet.py
cnocr/models/ocr_model.py
cnocr/ppocr/__init__.py
cnocr/ppocr/consts.py
cnocr/ppocr/pp_recognizer.py
cnocr/ppocr/rapid_recognizer.py
cnocr/ppocr/utility.py
cnocr/ppocr/postprocess/__init__.py
cnocr/ppocr/postprocess/rec_postprocess.py
cnocr/ppocr/utils/__init__.py
cnocr/ppocr/utils/chinese_cht_dict.txt
cnocr/ppocr/utils/en_dict.txt
cnocr/ppocr/utils/ppocr_keys_v1.txt
cnocr-2.3.2.2.data/data/chinese_cht_dict.txt
cnocr-2.3.2.2.data/data/en_dict.txt
cnocr-2.3.2.2.data/data/label_cn.txt
cnocr-2.3.2.2.data/data/label_number.txt
cnocr-2.3.2.2.data/data/ppocr_keys_v1.txt
cnocr-2.3.2.2.dist-info/LICENSE
cnocr-2.3.2.2.dist-info/METADATA
cnocr-2.3.2.2.dist-info/WHEEL
cnocr-2.3.2.2.dist-info/entry_points.txt
cnocr-2.3.2.2.dist-info/top_level.txt
cnocr-2.3.2.2.dist-info/RECORD
