Metadata-Version: 2.1
Name: cnocr
Version: 2.3.2.2
Summary: Python3 package for Chinese/English OCR, with small pretrained models
Home-page: https://github.com/breezedeus/cnocr
Author: breezedeus
Author-email: breezedeus@163.com
License: Apache 2.0
Platform: Mac
Platform: Linux
Platform: Windows
Classifier: Development Status :: 4 - Beta
Classifier: Operating System :: OS Independent
Classifier: Intended Audience :: Developers
Classifier: License :: OSI Approved :: Apache Software License
Classifier: Programming Language :: Python
Classifier: Programming Language :: Python :: Implementation
Classifier: Programming Language :: Python :: 3
Classifier: Programming Language :: Python :: 3.7
Classifier: Programming Language :: Python :: 3.8
Classifier: Programming Language :: Python :: 3.9
Classifier: Programming Language :: Python :: 3.10
Classifier: Topic :: Scientific/Engineering :: Artificial Intelligence
License-File: LICENSE
Requires-Dist: click
Requires-Dist: tqdm
Requires-Dist: torch>=1.8.0
Requires-Dist: torchvision>=0.9.0
Requires-Dist: numpy
Requires-Dist: pytorch-lightning>=2.0.0
Requires-Dist: wandb
Requires-Dist: torchmetrics
Requires-Dist: pillow>=5.3.0
Requires-Dist: onnx
Requires-Dist: cnstd>=1.2.6
Requires-Dist: rapidocr>=3.0
Provides-Extra: dev
Requires-Dist: albumentations; extra == "dev"
Requires-Dist: pip-tools; extra == "dev"
Requires-Dist: pytest; extra == "dev"
Requires-Dist: datasets[vision]; extra == "dev"
Provides-Extra: ort-cpu
Requires-Dist: onnxruntime; extra == "ort-cpu"
Provides-Extra: ort-gpu
Requires-Dist: onnxruntime-gpu; extra == "ort-gpu"
Provides-Extra: serve
Requires-Dist: uvicorn[standard]; extra == "serve"
Requires-Dist: fastapi; extra == "serve"
Requires-Dist: python-multipart; extra == "serve"
Requires-Dist: pydantic; extra == "serve"
